sanic_scheduler/__init__.py
sanic_scheduler/__meta__.py
sanic_scheduler-1.0.7.dist-info/METADATA
sanic_scheduler-1.0.7.dist-info/RECORD
sanic_scheduler-1.0.7.dist-info/WHEEL
sanic_scheduler-1.0.7.dist-info/top_level.txt
