Metadata-Version: 2.1
Name: sanic-scheduler
Version: 1.0.7
Summary: Running functions on a schedule for Sanic
Home-page: https://github.com/asmodius/sanic-scheduler
Author: Asmodius
Author-email: asmodius.a@gmail.com
License: MIT License
Keywords: sanic schedule
Platform: all
Classifier: Development Status :: 5 - Production/Stable
Classifier: Intended Audience :: Developers
Classifier: Operating System :: OS Independent
Classifier: License :: OSI Approved :: MIT License
Classifier: Topic :: Software Development :: Libraries :: Python Modules
Classifier: Programming Language :: Python
Classifier: Programming Language :: Python :: 3
Classifier: Programming Language :: Python :: 3.5
Classifier: Programming Language :: Python :: 3.6
Classifier: Programming Language :: Python :: 3.7
